gpt_synthesizer/__init__.py
gpt_synthesizer/app.py
gpt_synthesizer/generate_code.py
gpt_synthesizer/generate_main.py
gpt_synthesizer/main.py
gpt_synthesizer/model.py
gpt_synthesizer/parser.py
gpt_synthesizer/prompt.py
gpt_synthesizer/run_app.py
gpt_synthesizer/ui.py
gpt_synthesizer-0.0.4.dist-info/LICENSE
gpt_synthesizer-0.0.4.dist-info/METADATA
gpt_synthesizer-0.0.4.dist-info/WHEEL
gpt_synthesizer-0.0.4.dist-info/entry_points.txt
gpt_synthesizer-0.0.4.dist-info/top_level.txt
gpt_synthesizer-0.0.4.dist-info/RECORD
