Metadata-Version: 2.1
Name: gpt-synthesizer
Version: 0.0.4
Summary: Collaboratively build an entire codebase for any project with the help of an AI
Author-email: RoboCoach Technologies <robocoachtechnologies@gmail.com>
License: MIT License
Project-URL: Homepage, https://github.com/RoboCoachTechnologies/GPT-Synthesizer
Project-URL: Bug Tracker, https://github.com/RoboCoachTechnologies/GPT-Synthesizer/issues
Keywords: Large Language Models,AI-assisted Code Generation
Classifier: Development Status :: 2 - Pre-Alpha
Classifier: License :: OSI Approved :: MIT License
Classifier: Programming Language :: Python :: 3.8
Classifier: Programming Language :: Python :: 3.9
Classifier: Programming Language :: Python :: 3.10
Classifier: Programming Language :: Python :: 3.11
Classifier: Topic :: Scientific/Engineering :: Artificial Intelligence
Classifier: Topic :: Software Development :: Code Generators 
Requires-Python: >=3.8
License-File: LICENSE
Requires-Dist: langchain[openai]
Requires-Dist: streamlit
Provides-Extra: dev
Requires-Dist: pip-tools ; extra == 'dev'
Requires-Dist: pytest ; extra == 'dev'
